farness/__init__.py
farness/calibration.py
farness/cli.py
farness/framework.py
farness/storage.py
farness-0.1.0.dist-info/METADATA
farness-0.1.0.dist-info/WHEEL
farness-0.1.0.dist-info/entry_points.txt
farness-0.1.0.dist-info/top_level.txt
farness-0.1.0.dist-info/RECORD
