Metadata-Version: 2.4
Name: farness
Version: 0.1.0
Summary: Forecasting as a harness for decision-making
Author: Max Ghenis
License-Expression: MIT
Project-URL: Homepage, https://github.com/MaxGhenis/farness
Project-URL: Repository, https://github.com/MaxGhenis/farness
Project-URL: Issues, https://github.com/MaxGhenis/farness/issues
Keywords: forecasting,decision-making,calibration,prediction
Classifier: Development Status :: 3 - Alpha
Classifier: Intended Audience :: Developers
Classifier: Programming Language :: Python :: 3
Classifier: Programming Language :: Python :: 3.10
Classifier: Programming Language :: Python :: 3.11
Classifier: Programming Language :: Python :: 3.12
Requires-Python: >=3.10
Provides-Extra: dev
Requires-Dist: pytest>=7.0; extra == "dev"
Requires-Dist: pytest-cov>=4.0; extra == "dev"
Requires-Dist: black>=23.0; extra == "dev"
Requires-Dist: ruff>=0.1.0; extra == "dev"
